README.md
setup.py
pysndfx/__init__.py
pysndfx/dsp.py
pysndfx/sndfiles.py
pysndfx.egg-info/PKG-INFO
pysndfx.egg-info/SOURCES.txt
pysndfx.egg-info/dependency_links.txt
pysndfx.egg-info/requires.txt
pysndfx.egg-info/top_level.txt