Metadata-Version: 1.1
Name: pysndfx
Version: 0.2.1
Summary: Apply audio effects such as reverb and EQ directly to audio files or NumPy ndarrays.
Home-page: https://github.com/carlthome/python-audio-effects
Author: Carl Thomé
Author-email: carlthome@gmail.com
License: MIT
Keywords: audio music sound
Platform: UNKNOWN
Classifier: Development Status :: 3 - Alpha
Classifier: Intended Audience :: Developers
Classifier: Topic :: Multimedia :: Sound/Audio
Classifier: License :: OSI Approved :: MIT License
Classifier: Programming Language :: Python :: 2
Classifier: Programming Language :: Python :: 2.7
Classifier: Programming Language :: Python :: 3
Classifier: Programming Language :: Python :: 3.5
